pixiq/__init__.py
pixiq/photo_score.py
pixiq/pixiq.py
pixiq/psnr.py
pixiq/tiles.py
pixiq-0.5.0.dist-info/METADATA
pixiq-0.5.0.dist-info/WHEEL
pixiq-0.5.0.dist-info/licenses/LICENSE
pixiq-0.5.0.dist-info/RECORD
