Metadata-Version: 2.4
Name: pixiq
Version: 0.5.0
Summary: Intelligent image compression library with perceptual quality optimization
Project-URL: Documentation, https://github.com/bubaley/pixiq#readme
Project-URL: Homepage, https://github.com/bubaley/pixiq
Project-URL: Repository, https://github.com/bubaley/pixiq.git
Author-email: bubaley <bubaley.fu@gmail.com>
Maintainer-email: bubaley <bubaley.fu@gmail.com>
License: The MIT License (MIT)
License-File: LICENSE
Keywords: avif,compression,image,jpeg,perceptual,quality,webp
Classifier: Development Status :: 3 - Alpha
Classifier: Intended Audience :: Developers
Classifier: License :: OSI Approved :: MIT License
Classifier: Operating System :: OS Independent
Classifier: Programming Language :: Python :: 3 :: Only
Classifier: Programming Language :: Python :: 3.11
Classifier: Programming Language :: Python :: 3.12
Classifier: Programming Language :: Python :: 3.13
Classifier: Topic :: Multimedia :: Graphics
Classifier: Topic :: Software Development :: Libraries :: Python Modules
Requires-Python: <3.14,>=3.11
Requires-Dist: numpy>=2.3.4
Requires-Dist: pillow-avif-plugin>=1.5.2
Requires-Dist: pillow>=9.0.0
